ortools/__init__.py
ortools/.libs/libCbc.so.2
ortools/.libs/libCbcSolver.so.2
ortools/.libs/libCgl.so.0
ortools/.libs/libClp.so.1
ortools/.libs/libClpSolver.so.1
ortools/.libs/libCoinUtils.so.2
ortools/.libs/libOsi.so.0
ortools/.libs/libOsiCbc.so.2
ortools/.libs/libOsiClp.so.1
ortools/.libs/libabsl_base.so.2508.0.0
ortools/.libs/libabsl_city.so.2508.0.0
ortools/.libs/libabsl_civil_time.so.2508.0.0
ortools/.libs/libabsl_cord.so.2508.0.0
ortools/.libs/libabsl_cord_internal.so.2508.0.0
ortools/.libs/libabsl_cordz_functions.so.2508.0.0
ortools/.libs/libabsl_cordz_handle.so.2508.0.0
ortools/.libs/libabsl_cordz_info.so.2508.0.0
ortools/.libs/libabsl_crc32c.so.2508.0.0
ortools/.libs/libabsl_crc_cord_state.so.2508.0.0
ortools/.libs/libabsl_crc_cpu_detect.so.2508.0.0
ortools/.libs/libabsl_crc_internal.so.2508.0.0
ortools/.libs/libabsl_debugging_internal.so.2508.0.0
ortools/.libs/libabsl_decode_rust_punycode.so.2508.0.0
ortools/.libs/libabsl_demangle_internal.so.2508.0.0
ortools/.libs/libabsl_demangle_rust.so.2508.0.0
ortools/.libs/libabsl_die_if_null.so.2508.0.0
ortools/.libs/libabsl_examine_stack.so.2508.0.0
ortools/.libs/libabsl_exponential_biased.so.2508.0.0
ortools/.libs/libabsl_flags_commandlineflag.so.2508.0.0
ortools/.libs/libabsl_flags_commandlineflag_internal.so.2508.0.0
ortools/.libs/libabsl_flags_config.so.2508.0.0
ortools/.libs/libabsl_flags_internal.so.2508.0.0
ortools/.libs/libabsl_flags_marshalling.so.2508.0.0
ortools/.libs/libabsl_flags_parse.so.2508.0.0
ortools/.libs/libabsl_flags_private_handle_accessor.so.2508.0.0
ortools/.libs/libabsl_flags_program_name.so.2508.0.0
ortools/.libs/libabsl_flags_reflection.so.2508.0.0
ortools/.libs/libabsl_flags_usage.so.2508.0.0
ortools/.libs/libabsl_flags_usage_internal.so.2508.0.0
ortools/.libs/libabsl_graphcycles_internal.so.2508.0.0
ortools/.libs/libabsl_hash.so.2508.0.0
ortools/.libs/libabsl_hashtablez_sampler.so.2508.0.0
ortools/.libs/libabsl_int128.so.2508.0.0
ortools-9.15.6755.dist-info/METADATA
ortools-9.15.6755.dist-info/WHEEL
ortools-9.15.6755.dist-info/top_level.txt
ortools-9.15.6755.dist-info/RECORD
ortools-9.15.6755.dist-info/licenses/LICENSE
